titus_cli/__init__.py
titus_cli/color_blocks_writers.py
titus_cli/constants.py
titus_cli/css_files/reset.css
titus_cli/css_generators.py
titus_cli/helpers.py
titus_cli/main.py
titus_cli/other_blocks_writers.py
titus_cli/size_blocks_writers.py
titus_cli-0.1.1.dist-info/LICENSE
titus_cli-0.1.1.dist-info/METADATA
titus_cli-0.1.1.dist-info/WHEEL
titus_cli-0.1.1.dist-info/entry_points.txt
titus_cli-0.1.1.dist-info/RECORD
