Metadata-Version: 2.1
Name: titus-cli
Version: 0.1.1
Summary: CLI for the Titus CSS toolkit; it generates the base CSS files.
License: LICENSE
Author: Lucas Sorribes
Author-email: lucas@luxor.dev
Requires-Python: >=3.8,<4.0
Classifier: License :: Other/Proprietary License
Classifier: Programming Language :: Python :: 3
Classifier: Programming Language :: Python :: 3.8
Classifier: Programming Language :: Python :: 3.9
Classifier: Programming Language :: Python :: 3.10
Classifier: Programming Language :: Python :: 3.11
Classifier: Programming Language :: Python :: 3.12
Requires-Dist: pyinquirer (>=1.0.3,<2.0.0)
Requires-Dist: rich (>=13.9.2,<14.0.0)
Requires-Dist: typer (>=0.12.5,<0.13.0)
